MANIFEST.in
README.rst
setup.py
vesna_alh_auth_proxy
vesna_alh_auth_proxy.conf
test/__init__.py
test/test_omf.py
vesna/__init__.py
vesna/omf/__init__.py
vesna/omf/proxy.py
vesna_alhauthproxy.egg-info/PKG-INFO
vesna_alhauthproxy.egg-info/SOURCES.txt
vesna_alhauthproxy.egg-info/dependency_links.txt
vesna_alhauthproxy.egg-info/entry_points.txt
vesna_alhauthproxy.egg-info/namespace_packages.txt
vesna_alhauthproxy.egg-info/requires.txt
vesna_alhauthproxy.egg-info/top_level.txt