Metadata-Version: 1.0
Name: vesna-alhauthproxy
Version: 1.0.5
Summary: ALH authorization proxy for OMF
Home-page: UNKNOWN
Author: Tomaz Solc
Author-email: tomaz.solc@ijs.si
License: GPL
Platform: UNKNOWN
